EpitechApi/Epitech.py
EpitechApi/__init__.py
EpitechApi-0.0.1.dist-info/LICENSE
EpitechApi-0.0.1.dist-info/METADATA
EpitechApi-0.0.1.dist-info/WHEEL
EpitechApi-0.0.1.dist-info/top_level.txt
EpitechApi-0.0.1.dist-info/RECORD
