Metadata-Version: 2.1
Name: EpitechApi
Version: 0.0.1
Summary: A small wrapper for Epitech Api
Home-page: https://github.com/Kyashar/EpitechPythonApi
Author: Erwan Bernard
Author-email: erwan.bernard079@gmail.com
License: UNKNOWN
Platform: UNKNOWN
Classifier: Programming Language :: Python :: 3
Classifier: License :: OSI Approved :: MIT License
Classifier: Operating System :: OS Independent
Requires-Dist: requests (>=2.19.1)
